{
  "timeZone": "America/Chicago",
  "dependencies": {},
  "exceptionLogging": "STACKDRIVER",
  "runtimeVersion": "V8",
  "oauthScopes": [
    "https://www.googleapis.com/auth/drive"
  ],
  "addOns": {
    "common": {
      "name": "SVG Converter",
      "logoUrl": "https://cmsv2-assets.apptegy.net/uploads/5877/logo/3225/Clippers-NoText-CMYK.png",
      "homepageTrigger": {
        "runFunction": "onOpen"
      }
    },
    "gmail": {},
    "drive": {},
    "calendar": {},
    "docs": {},
    "sheets": {},
    "slides": {}
  }
}